epyg/Applications.py
epyg/EpyG.py
epyg/Operators.py
epyg/__init__.py
epyg-0.2.0.dist-info/LICENSE
epyg-0.2.0.dist-info/WHEEL
epyg-0.2.0.dist-info/METADATA
epyg-0.2.0.dist-info/RECORD
