Metadata-Version: 2.1
Name: epyg
Version: 0.2.0
Summary: Python implementation of the Extended Phase Graph algorithm for simulation of MRI signals
Home-page: https://github.com/brennerd11/EpyG
License: MIT
Keywords: MRI,simulation
Author: Daniel Brenner
Requires-Python: >=3.8,<4.0
Classifier: Development Status :: 4 - Beta
Classifier: Intended Audience :: Science/Research
Classifier: License :: OSI Approved :: MIT License
Classifier: Programming Language :: Python :: 3
Classifier: Programming Language :: Python :: 3.10
Classifier: Programming Language :: Python :: 3.8
Classifier: Programming Language :: Python :: 3.9
Requires-Dist: numpy (>=1.23.1,<2.0.0)
Project-URL: Repository, https://github.com/brennerd11/EpyG
